cli/__init__.py
cli/api/__init__.py
cli/api/decorators.py
cli/api/hooks.py
cli/buckets/__init__.py
cli/buckets/commands.py
cli/config.py
cli/datasets/__init__.py
cli/datasets/commands.py
cli/datasets/preprocessor/__init__.py
cli/datasets/preprocessor/config/__init__.py
cli/datasets/preprocessor/config/cnn_pca/__init__.py
cli/datasets/preprocessor/config/cnn_pca/case.py
cli/datasets/preprocessor/config/cnn_pca/common.py
cli/datasets/preprocessor/config/cnn_pca/step.py
cli/datasets/preprocessor/config/facilities/__init__.py
cli/datasets/preprocessor/config/facilities/case.py
cli/datasets/preprocessor/config/facilities/common.py
cli/datasets/preprocessor/config/facilities/step.py
cli/datasets/preprocessor/config/well_model/__init__.py
cli/datasets/preprocessor/config/well_model/case.py
cli/datasets/preprocessor/config/well_model/common.py
cli/datasets/preprocessor/config/well_model/step.py
cli/datasets/preprocessor/init_keywords.json
cli/datasets/preprocessor/preprocess_functions.py
cli/datasets/preprocessor/process_step.py
cli/datasets/preprocessor/well_init_keywords.json
cli/datasets/sources/__init__.py
cli/datasets/sources/az.py
cli/datasets/sources/common.py
cli/datasets/sources/local.py
cli/datasets/sources/s3.py
cli/datasets/upload.py
cli/debugger/__init__.py
cli/debugger/commands.py
cli/debugger/init_keyword_check.py
cli/debugger/restart_keyword_check.py
cli/jobs/__init__.py
cli/jobs/commands.py
cli/jobs/list.py
cli/runtime.py
cli/simulations/__init__.py
cli/simulations/commands.py
cli/simulations/create.py
cli/simulations/dependencySolver.py
cli/simulations/opm.py
cli/utils/__init__.py
cli/utils/files.py
cli/utils/sssh.py
cli/utils/sync.py
logging.ini
proteus_cli-1.1.44.dist-info/METADATA
proteus_cli-1.1.44.dist-info/WHEEL
proteus_cli-1.1.44.dist-info/entry_points.txt
proteus_cli-1.1.44.dist-info/RECORD
