Metadata-Version: 2.1
Name: proteus-cli
Version: 1.1.44
Summary: 
Requires-Python: >=3.8,<3.9
Classifier: Programming Language :: Python :: 3
Classifier: Programming Language :: Python :: 3.8
Requires-Dist: azure-identity (>=1.12.0,<2.0.0)
Requires-Dist: azure-storage-blob (>=12.8.1,<13.0.0)
Requires-Dist: boto3 (>=1.17.79,<2.0.0)
Requires-Dist: click (>=8.0.0,<9.0.0)
Requires-Dist: cryptography (>=42.0.4,<43.0.0)
Requires-Dist: jwt (>=1.2.0,<2.0.0)
Requires-Dist: markupsafe (==2.0.1)
Requires-Dist: proteus-preprocessing (==0.4.9)
Requires-Dist: proteus-runtime (==0.5.20)
Requires-Dist: pycryptodome (>=3.10.1,<4.0.0)
Requires-Dist: readchar (>=3.0.4,<4.0.0)
Requires-Dist: tables (==3.8.0)
Requires-Dist: tabulate (>=0.8.9,<0.9.0)
Requires-Dist: tqdm (>=4.61.0,<5.0.0)
